cexprtk/_functionargs.py
cexprtk/_symbol_table.cpython-311-darwin.so
cexprtk/__init__.py
cexprtk/_custom_function_callbacks.cpython-311-darwin.so
cexprtk/_cexprtk.cpython-311-darwin.so
cexprtk/_exceptions.py
cexprtk-0.4.2.dist-info/RECORD
cexprtk-0.4.2.dist-info/WHEEL
cexprtk-0.4.2.dist-info/top_level.txt
cexprtk-0.4.2.dist-info/METADATA
cexprtk-0.4.2.dist-info/licenses/LICENSE
