Metadata-Version: 2.4
Name: cexprtk
Version: 0.4.2
Summary: Mathematical expression parser: cython wrapper around the 'C++ Mathematical Expression Toolkit Library' 
Home-page: https://github.com/mjdrushton/cexprtk
Download-URL: https://github.com/mjdrushton/cexprtk/archive/0.4.2.tar.gz
Author: M.J.D. Rushton
Author-email: m.j.d.rushton@gmail.com
License: CPL
Keywords: math,formula,parser,arithmetic,evaluate
Classifier: License :: OSI Approved :: Common Public License
Classifier: Programming Language :: C++
Classifier: Programming Language :: Python :: 3.9
Classifier: Programming Language :: Python :: 3.10
Classifier: Programming Language :: Python :: 3.11
Classifier: Programming Language :: Python :: 3.12
Classifier: Programming Language :: Python :: 3.13
Classifier: Programming Language :: Python :: 3.14
Classifier: Programming Language :: Python :: 3.15
Classifier: Programming Language :: Cython
Classifier: Topic :: Scientific/Engineering :: Mathematics
License-File: LICENSE
Dynamic: author
Dynamic: author-email
Dynamic: classifier
Dynamic: description
Dynamic: description-content-type
Dynamic: download-url
Dynamic: home-page
Dynamic: keywords
Dynamic: license
Dynamic: license-file
Dynamic: summary
